sblue/__init__.py
sendinblue_logger-1.0.0.dist-info/LICENSE
sendinblue_logger-1.0.0.dist-info/WHEEL
sendinblue_logger-1.0.0.dist-info/METADATA
sendinblue_logger-1.0.0.dist-info/RECORD
