Metadata-Version: 2.1
Name: sendinblue-logger
Version: 1.0.0
Summary: Send log messages to sendinblue's transactional email service.
Home-page: https://github.com/calwarhurst/sendinblue-logger
License: MIT
Author: Cal Warhurst
Requires-Python: >=3.9,<4.0
Classifier: License :: OSI Approved :: MIT License
Classifier: Operating System :: OS Independent
Classifier: Programming Language :: Python :: 3
Classifier: Programming Language :: Python :: 3.10
Classifier: Programming Language :: Python :: 3.9
Requires-Dist: requests (>=2.28.1,<3.0.0)
Project-URL: Repository, https://github.com/calwarhurst/sendinblue-logger
